pipelinex/__init__.py
pipelinex/utils.py
pipelinex/extras/__init__.py
pipelinex/extras/datasets/__init__.py
pipelinex/extras/datasets/core.py
pipelinex/extras/datasets/httpx/__init__.py
pipelinex/extras/datasets/httpx/async_api_dataset.py
pipelinex/extras/datasets/opencv/__init__.py
pipelinex/extras/datasets/opencv/images_dataset.py
pipelinex/extras/datasets/pandas/__init__.py
pipelinex/extras/datasets/pandas/csv_local.py
pipelinex/extras/datasets/pandas/efficient_csv_local.py
pipelinex/extras/datasets/pandas/fixed_width_csv_dataset.py
pipelinex/extras/datasets/pandas/histgram.py
pipelinex/extras/datasets/pandas/pandas_cat_matrix.py
pipelinex/extras/datasets/pandas/pandas_describe.py
pipelinex/extras/datasets/pandas_profiling/__init__.py
pipelinex/extras/datasets/pandas_profiling/pandas_profiling.py
pipelinex/extras/datasets/pillow/__init__.py
pipelinex/extras/datasets/pillow/images_dataset.py
pipelinex/extras/datasets/requests/__init__.py
pipelinex/extras/datasets/requests/api_dataset.py
pipelinex/extras/datasets/seaborn/__init__.py
pipelinex/extras/datasets/seaborn/seaborn_pairplot.py
pipelinex/extras/datasets/torchvision/__init__.py
pipelinex/extras/datasets/torchvision/iterable_images_dataset.py
pipelinex/extras/decorators/__init__.py
pipelinex/extras/decorators/decorators.py
pipelinex/extras/decorators/memory_profiler.py
pipelinex/extras/decorators/nvml_profiler.py
pipelinex/extras/decorators/pandas_decorators.py
pipelinex/extras/hooks/__init__.py
pipelinex/extras/hooks/add_catalog_dict.py
pipelinex/extras/hooks/add_transformers.py
pipelinex/extras/ops/__init__.py
pipelinex/extras/ops/allennlp_ops.py
pipelinex/extras/ops/argparse_ops.py
pipelinex/extras/ops/numpy_ops.py
pipelinex/extras/ops/opencv_ops.py
pipelinex/extras/ops/pandas_ops.py
pipelinex/extras/ops/pytorch_ops.py
pipelinex/extras/ops/shap_ops.py
pipelinex/extras/ops/skimage_ops.py
pipelinex/extras/ops/sklearn_ops.py
pipelinex/extras/ops/ignite/__init__.py
pipelinex-0.7.9.dist-info/LICENSE
pipelinex-0.7.9.dist-info/METADATA
pipelinex-0.7.9.dist-info/WHEEL
pipelinex-0.7.9.dist-info/top_level.txt
pipelinex-0.7.9.dist-info/RECORD
