Metadata-Version: 2.1
Name: pipelinex
Version: 0.7.9
Summary: PipelineX: Python package to build ML pipelines for experimentation with Kedro, MLflow, and more
Home-page: https://github.com/Minyus/pipelinex
Author: Yusuke Minami
Author-email: me@minyus.github.com
License: Apache Software License (Apache 2.0)
Keywords: pipelines,machine learning,deep learning,data science,data engineering
Classifier: Development Status :: 3 - Alpha
Classifier: Natural Language :: English
Classifier: Programming Language :: Python :: 3.7
Classifier: Programming Language :: Python :: 3.8
Classifier: Programming Language :: Python :: 3.9
Classifier: Programming Language :: Python :: 3.10
Classifier: Programming Language :: Python :: 3.11
Classifier: Operating System :: OS Independent
License-File: LICENSE
Requires-Dist: numpy
Requires-Dist: flatten-dict (>=0.3.0)
Provides-Extra: dev
Requires-Dist: isort ; extra == 'dev'
Requires-Dist: black ; extra == 'dev'
Requires-Dist: flake8 ; extra == 'dev'
Requires-Dist: twine ; extra == 'dev'
Requires-Dist: keyrings.alt (>=3.4.0) ; extra == 'dev'
Requires-Dist: featuretools ; extra == 'dev'
Requires-Dist: pytest ; extra == 'dev'
Requires-Dist: pytest-cov ; extra == 'dev'
Requires-Dist: pytest-mock ; extra == 'dev'
Requires-Dist: requests-mock (>=1.8.0) ; extra == 'dev'
Requires-Dist: Sphinx (==3.5.1) ; extra == 'dev'
Requires-Dist: Jinja2 (==2.11.3) ; extra == 'dev'
Requires-Dist: markupsafe (==2.0.1) ; extra == 'dev'
Requires-Dist: sphinx-rtd-theme (==0.5.1) ; extra == 'dev'
Requires-Dist: recommonmark (==0.7.1) ; extra == 'dev'
Requires-Dist: sphinx-autodoc-typehints (==1.11.1) ; extra == 'dev'
Requires-Dist: typed-ast (==1.4.2) ; extra == 'dev'
Requires-Dist: sphinx-copybutton (==0.3.1) ; extra == 'dev'
Requires-Dist: kedro ; extra == 'dev'
Requires-Dist: kedro-datasets ; extra == 'dev'
Requires-Dist: pandas ; extra == 'dev'
Requires-Dist: matplotlib ; extra == 'dev'
Requires-Dist: seaborn ; extra == 'dev'
Requires-Dist: pandas-profiling ; extra == 'dev'
Requires-Dist: Pillow ; extra == 'dev'
Requires-Dist: torch ; extra == 'dev'
Requires-Dist: torch-vision ; extra == 'dev'
Requires-Dist: pytorch-ignite ; extra == 'dev'
Requires-Dist: opencv-python ; extra == 'dev'
Requires-Dist: opencv-contrib-python ; extra == 'dev'
Requires-Dist: requests ; extra == 'dev'
Requires-Dist: httpx ; extra == 'dev'
Requires-Dist: mlflow ; extra == 'dev'
Requires-Dist: plotly ; extra == 'dev'
Requires-Dist: scikit-learn ; extra == 'dev'
Requires-Dist: scikit-image ; extra == 'dev'
Requires-Dist: memory-profiler ; extra == 'dev'
Requires-Dist: pynvml ; extra == 'dev'
Requires-Dist: flatten-dict ; extra == 'dev'
Requires-Dist: nested-lookup ; extra == 'dev'
Requires-Dist: numpy ; extra == 'dev'
Requires-Dist: flatten-dict (>=0.3.0) ; extra == 'dev'
Provides-Extra: docs
Requires-Dist: Sphinx (==3.5.1) ; extra == 'docs'
Requires-Dist: Jinja2 (==2.11.3) ; extra == 'docs'
Requires-Dist: markupsafe (==2.0.1) ; extra == 'docs'
Requires-Dist: sphinx-rtd-theme (==0.5.1) ; extra == 'docs'
Requires-Dist: recommonmark (==0.7.1) ; extra == 'docs'
Requires-Dist: sphinx-autodoc-typehints (==1.11.1) ; extra == 'docs'
Requires-Dist: typed-ast (==1.4.2) ; extra == 'docs'
Requires-Dist: sphinx-copybutton (==0.3.1) ; extra == 'docs'
Requires-Dist: kedro ; extra == 'docs'
Requires-Dist: kedro-datasets ; extra == 'docs'
Requires-Dist: pandas ; extra == 'docs'
Requires-Dist: matplotlib ; extra == 'docs'
Requires-Dist: seaborn ; extra == 'docs'
Requires-Dist: pandas-profiling ; extra == 'docs'
Requires-Dist: Pillow ; extra == 'docs'
Requires-Dist: torch ; extra == 'docs'
Requires-Dist: torch-vision ; extra == 'docs'
Requires-Dist: pytorch-ignite ; extra == 'docs'
Requires-Dist: opencv-python ; extra == 'docs'
Requires-Dist: opencv-contrib-python ; extra == 'docs'
Requires-Dist: requests ; extra == 'docs'
Requires-Dist: httpx ; extra == 'docs'
Requires-Dist: mlflow ; extra == 'docs'
Requires-Dist: plotly ; extra == 'docs'
Requires-Dist: scikit-learn ; extra == 'docs'
Requires-Dist: scikit-image ; extra == 'docs'
Requires-Dist: memory-profiler ; extra == 'docs'
Requires-Dist: pynvml ; extra == 'docs'
Requires-Dist: flatten-dict ; extra == 'docs'
Requires-Dist: nested-lookup ; extra == 'docs'
Requires-Dist: numpy ; extra == 'docs'
Requires-Dist: flatten-dict (>=0.3.0) ; extra == 'docs'
Provides-Extra: optional
Requires-Dist: kedro ; extra == 'optional'
Requires-Dist: kedro-datasets ; extra == 'optional'
Requires-Dist: pandas ; extra == 'optional'
Requires-Dist: matplotlib ; extra == 'optional'
Requires-Dist: seaborn ; extra == 'optional'
Requires-Dist: pandas-profiling ; extra == 'optional'
Requires-Dist: Pillow ; extra == 'optional'
Requires-Dist: torch ; extra == 'optional'
Requires-Dist: torch-vision ; extra == 'optional'
Requires-Dist: pytorch-ignite ; extra == 'optional'
Requires-Dist: opencv-python ; extra == 'optional'
Requires-Dist: opencv-contrib-python ; extra == 'optional'
Requires-Dist: requests ; extra == 'optional'
Requires-Dist: httpx ; extra == 'optional'
Requires-Dist: mlflow ; extra == 'optional'
Requires-Dist: plotly ; extra == 'optional'
Requires-Dist: scikit-learn ; extra == 'optional'
Requires-Dist: scikit-image ; extra == 'optional'
Requires-Dist: memory-profiler ; extra == 'optional'
Requires-Dist: pynvml ; extra == 'optional'
Requires-Dist: flatten-dict ; extra == 'optional'
Requires-Dist: nested-lookup ; extra == 'optional'
Requires-Dist: numpy ; extra == 'optional'
Requires-Dist: flatten-dict (>=0.3.0) ; extra == 'optional'
